geoca/__init__.py
geoca/cellularautomata.py
geoca/geoca.py
geoca/rasterconvert.py
geoca-0.0.11.dist-info/LICENSE
geoca-0.0.11.dist-info/METADATA
geoca-0.0.11.dist-info/WHEEL
geoca-0.0.11.dist-info/entry_points.txt
geoca-0.0.11.dist-info/top_level.txt
geoca-0.0.11.dist-info/RECORD
