Metadata-Version: 2.1
Name: geoca
Version: 0.0.11
Summary: A Python module for CA models based on geo-raster data
Author-email: Haorui Jiang <jianghr0321@163.com>
License: MIT License
Project-URL: Homepage, https://github.com/Haorui-Jiang/geoca
Keywords: geoca
Classifier: Intended Audience :: Developers
Classifier: License :: OSI Approved :: MIT License
Classifier: Natural Language :: English
Classifier: Programming Language :: Python :: 3.8
Classifier: Programming Language :: Python :: 3.9
Classifier: Programming Language :: Python :: 3.10
Classifier: Programming Language :: Python :: 3.11
Classifier: Programming Language :: Python :: 3.12
Requires-Python: >=3.8
License-File: LICENSE
Requires-Dist: numpy
Requires-Dist: rasterio
Requires-Dist: tqdm
Provides-Extra: all
Requires-Dist: geoca[extra] ; extra == 'all'
Provides-Extra: extra
Requires-Dist: pandas ; extra == 'extra'
